{
	"episodes_list": [
		{
		   "number": "",
		   "title": "Episodio 01",
		   "links": [
			   {
				"url": "https://akvideo.stream/video/8wqo4aksh0cm"
			   }
			]
		 },
    {
		   "number": "",
		   "title": "Episodio 02",
		   "links": [
			   {
				"url": "https://akvideo.stream/video/0vd69pv8cwl3"
			   }
			]
		 },
    {
		   "number": "",
		   "title": "Episodio 03",
		   "links": [
			   {
				"url": "https://akvideo.stream/video/vu82w186ba9m"
			   }
			]
		 },
     {
		   "number": "",
		   "title": "Episodio 04",
		   "links": [
			   {
				"url": "https://akvideo.stream/video/s4pc6f82zr7v"
			   }
			]
		 },
    {
		   "number": "",
		   "title": "Episodio 05",
		   "links": [
			   {
				"url": "https://akvideo.stream/video/pi2f8rm8unve"
			   }
			]
		 },
     {
		   "number": "",
		   "title": "Episodio 06",
		   "links": [
			   {
				"url": "https://akvideo.stream/video/gw541eofgnvf"
			   }
			]
		 },
     {
		   "number": "",
		   "title": "Episodio 07",
		   "links": [
			   {
				"url": "https://akvideo.stream/video/ncqh3e58fzzb"
			   }
			]
		 },
     {
		   "number": "",
		   "title": "Episodio 08",
		   "links": [
			   {
				"url": "https://akvideo.stream/video/l7e2nbkp7v5v"
			   }
			]
		 },
    {
		   "number": "",
		   "title": "Episodio 09",
		   "links": [
			   {
				"url": "https://akvideo.stream/video/0r3rp3csu3fw"
			   }
			]
		 },
      {
		   "number": "",
		   "title": "Episodio 10",
		   "links": [
			   {
				"url": "https://akvideo.stream/video/mv1b1w3d7kvr"
			   }
			]
		 },
		 {
		   "number": "",
		   "title": "Episodio 11",
		   "links": [
			   {
				"url": "https://akvideo.stream/video/t4ze4alteket"
			   }
			]
		 },
		 {
		   "number": "",
		   "title": "Episodio 12",
		   "links": [
			   {
				"url": "https://akvideo.stream/video/hw1b7hbhu4iz"
			   }
			]
		 },
		 {
		   "number": "",
		   "title": "Episodio 13",
		   "links": [
			   {
				"url": "https://akvideo.stream/video/ikmhibils8sb"
			   }
			]
		 },
		 {
		   "number": "",
		   "title": "Episodio 14",
		   "links": [
			   {
				"url": "https://akvideo.stream/video/s44gl68a5cv0"
			   }
			]
		 },
		{
		   "number": "",
		   "title": "Episodio 15",
		   "links": [
			   {
				"url": "https://akvideo.stream/video/s68cozmfctkh"
			   }
			]
		 },
		{
		   "number": "",
		   "title": "Episodio 16",
		   "links": [
			   {
				"url": "https://akvideo.stream/video/nqb0n57mqolo"
			   }
			]
		 },
		{
		   "number": "",
		   "title": "Episodio 17",
		   "links": [
			   {
				"url": "https://akvideo.stream/video/obqse8z9k80k"
			   }
			]
		 },
		{
		   "number": "",
		   "title": "Episodio 18",
		   "links": [
			   {
				"url": "https://akvideo.stream/video/dmwqigrbeaop"
			   }
			]
		 },
		{
		   "number": "",
		   "title": "Episodio 19",
		   "links": [
			   {
				"url": "https://akvideo.stream/video/qekvrr1oqofv"
			   }
			]
		 },
		{
		   "number": "",
		   "title": "Episodio 20",
		   "links": [
			   {
				"url": "https://akvideo.stream/video/6g968e1pi264"
			   }
			]
		 },
		{
		   "number": "",
		   "title": "Episodio 21",
		   "links": [
			   {
				"url": "https://akvideo.stream/video/136pliitn59s"
			   }
			]
		 },
		{
		   "number": "",
		   "title": "Episodio 22",
		   "links": [
			   {
				"url": "https://akvideo.stream/video/c84zgfvn5shd"
			   }
			]
		 },
		{
		   "number": "",
		   "title": "Episodio 23",
		   "links": [
			   {
				"url": "https://akvideo.stream/video/1v3hgn0dg1c3"
			   }
			]
		 },
		{
		   "number": "",
		   "title": "Episodio 24",
		   "links": [
			   {
				"url": "https://akvideo.stream/video/lqg5unpvn1ta"
			   }
			]
		 },
		{
		   "number": "",
		   "title": "Episodio 25",
		   "links": [
			   {
				"url": "https://akvideo.stream/video/el9p7ig541sm"
			   }
			]
		 },
		{
		   "number": "",
		   "title": "Episodio 26",
		   "links": [
			   {
				"url": "https://akvideo.stream/video/81rbzueq0va0"
			   }
			]
		 },
		{
		   "number": "",
		   "title": "Episodio 27",
		   "links": [
			   {
				"url": "https://akvideo.stream/video/9inthf5p55mk"
			   }
			]
		 },
		{
		   "number": "",
		   "title": "Episodio 28",
		   "links": [
			   {
				"url": "https://wstream.video/video6zvimpy52/tepu7glt657v"
			   }
			]
		 },
		{
		   "number": "",
		   "title": "Episodio 29",
		   "links": [
			   {
				"url": "https://akvideo.stream/video/87or69l47bi7"
			   }
			]
		 },
		{
		   "number": "",
		   "title": "Episodio 30",
		   "links": [
			   {
				"url": "https://akvideo.stream/video/kdv0ha6e237f"
			   }
			]
		 },
		{
		   "number": "",
		   "title": "Episodio 31",
		   "links": [
			   {
				"url": "https://akvideo.stream/video/ibw2envdk55k"
			   }
			]
		 },
		{
		   "number": "",
		   "title": "Episodio 32",
		   "links": [
			   {
				"url": "https://akvideo.stream/video/5pt59p2wn8ww"
			   }
			]
		 },
		{
		   "number": "",
		   "title": "Episodio 33",
		   "links": [
			   {
				"url": "https://akvideo.stream/video/qbk0k4u27ac3"
			   }
			]
		 },
		{
		   "number": "",
		   "title": "Episodio 34",
		   "links": [
			   {
				"url": "https://akvideo.stream/video/our49quq8zqn"
			   }
			]
		 },
		{
		   "number": "",
		   "title": "Episodio 35",
		   "links": [
			   {
				"url": "https://akvideo.stream/video/g4pb2helr9vf"
			   }
			]
		 },
		{
		   "number": "",
		   "title": "Episodio 36",
		   "links": [
			   {
				"url": "https://akvideo.stream/video/43mtig5f7c28"
			   }
			]
		 },
		{
		   "number": "",
		   "title": "Episodio 37",
		   "links": [
			   {
				"url": "https://akvideo.stream/video/e1p1644v89ko"
			   }
			]
		 },
		{
		   "number": "",
		   "title": "Episodio 38",
		   "links": [
			   {
				"url": "https://akvideo.stream/video/0bfthtr70a8d"
			   }
			]
		 },
		{
		   "number": "",
		   "title": "Episodio 39",
		   "links": [
			   {
				"url": "https://akvideo.stream/video/u18utov8o9fl"
			   }
			]
		 },
		{
		   "number": "",
		   "title": "Episodio 40",
		   "links": [
			   {
				"url": "https://akvideo.stream/video/9tf05rf7d3sa"
			   }
			]
		 }
    ]
}   
