{
	"episodes_list": [
		{
		   "number": "",
		   "title": "Episodio 01",
		   "links": [
			   {
				"url": "https://akvideo.stream/video/dvsmbfougd7s"
			   }
			]
		 },
    	{
		   "number": "",
		   "title": "Episodio 02",
		   "links": [
			   {
				"url": "https://akvideo.stream/video/ntic1vdh43rl"
			   }
			]
		 },
    	{
		   "number": "",
		   "title": "Episodio 03",
		   "links": [
			   {
				"url": "https://akvideo.stream/video/hvhnfbgmmkn0"
			   }
			]
		 },
    	{
		   "number": "",
		   "title": "Episodio 04",
		   "links": [
			   {
				"url": "https://akvideo.stream/video/n2g54idok871"
			   }
			]
		 },
    	{
		   "number": "",
		   "title": "Episodio 05",
		   "links": [
			   {
				"url": "https://akvideo.stream/video/r6f4qvs7m5si"
			   }
			]
		 },
    	{
		   "number": "",
		   "title": "Episodio 06",
		   "links": [
			   {
				"url": "https://akvideo.stream/video/pp9256n5umwq"
			   }
			]
		 },
    	{
		   "number": "",
		   "title": "Episodio 07",
		   "links": [
			   {
				"url": "https://akvideo.stream/video/64anatn6mh3c"
			   }
			]
		 },
    	{
		   "number": "",
		   "title": "Episodio 08",
		   "links": [
			   {
				"url": "https://akvideo.stream/video/pg795soqlk1d"
			   }
			]
		 },
    	{
		   "number": "",
		   "title": "Episodio 09",
		   "links": [
			   {
				"url": "https://akvideo.stream/video/2bszs8iqthwt"
			   }
			]
		 },
    	{
		   "number": "",
		   "title": "Episodio 10",
		   "links": [
			   {
				"url": "https://akvideo.stream/video/0700ob9howgt"
			   }
			]
		 },
		{
		   "number": "",
		   "title": "Episodio 11",
		   "links": [
			   {
				"url": "https://akvideo.stream/video/zrm94z2p0v3a"
			   }
			]
		 },
    	{
		   "number": "",
		   "title": "Episodio 12",
		   "links": [
			   {
				"url": "https://akvideo.stream/video/7r0fufvzv4qs"
			   }
			]
		 },
    	{
		   "number": "",
		   "title": "Episodio 13",
		   "links": [
			   {
				"url": "https://akvideo.stream/video/aitlkz3bq2kz"
			   }
			]
		 },
    	{
		   "number": "",
		   "title": "Episodio 14",
		   "links": [
			   {
				"url": "https://akvideo.stream/video/cfhs7lovs54c"
			   }
			]
		 },
    	{
		   "number": "",
		   "title": "Episodio 15",
		   "links": [
			   {
				"url": "https://akvideo.stream/video/3wtzwbtpdlkm"
			   }
			]
		 },
    	{
		   "number": "",
		   "title": "Episodio 16",
		   "links": [
			   {
				"url": "https://akvideo.stream/video/hsiwh790i16t"
			   }
			]
		 },
    	{
		   "number": "",
		   "title": "Episodio 17",
		   "links": [
			   {
				"url": "https://akvideo.stream/video/e7egv0cif25z"
			   }
			]
		 },
    	{
		   "number": "",
		   "title": "Episodio 18",
		   "links": [
			   {
				"url": "https://akvideo.stream/video/e3d46682fw3s"
			   }
			]
		 },
    	{
		   "number": "",
		   "title": "Episodio 19",
		   "links": [
			   {
				"url": "https://akvideo.stream/video/4bsgts1ibcic"
			   }
			]
		 },
    	{
		   "number": "",
		   "title": "Episodio 20",
		   "links": [
			   {
				"url": "https://akvideo.stream/video/ztl3i6uasr9a"
			   }
			]
		 }
		
       ]
}   
