{
	"episodes_list": [
		{
		   "number": "",
		   "title": "Episodio 01",
		   "links": [
			   {
				"url": "https://wstream.video/video6zvimpy52/5r39bcm729ug"
			   }
			]
		 },
    	{
		   "number": "",
		   "title": "Episodio 02",
		   "links": [
			   {
				"url": "https://wstream.video/video6zvimpy52/c77pxrxlrz8l"
			   }
			]
		 },
    	{
		   "number": "",
		   "title": "Episodio 03",
		   "links": [
			   {
				"url": "https://wstream.video/video6zvimpy52/1gg8oxc5o0v4"
			   }
			]
		 },
    	{
		   "number": "",
		   "title": "Episodio 04",
		   "links": [
			   {
				"url": "https://wstream.video/video6zvimpy52/jes7weazkj5k"
			   }
			]
		 },
    	{
		   "number": "",
		   "title": "Episodio 05",
		   "links": [
			   {
				"url": "https://wstream.video/video6zvimpy52/tk33vypew9p4"
			   }
			]
		 },
    	{
		   "number": "",
		   "title": "Episodio 06",
		   "links": [
			   {
				"url": "https://wstream.video/video6zvimpy52/zoxhkh71pxkf"
			   }
			]
		 },
    	{
		   "number": "",
		   "title": "Episodio 07",
		   "links": [
			   {
				"url": "https://wstream.video/video6zvimpy52/a3syri73otgv"
			   }
			]
		 },
    	{
		   "number": "",
		   "title": "Episodio 08",
		   "links": [
			   {
				"url": "https://wstream.video/video6zvimpy52/p51b4tklgggu"
			   }
			]
		 },
    	{
		   "number": "",
		   "title": "Episodio 09",
		   "links": [
			   {
				"url": "https://wstream.video/video6zvimpy52/5l7zqat6afhi"
			   }
			]
		 },
    	{
		   "number": "",
		   "title": "Episodio 10",
		   "links": [
			   {
				"url": "https://wstream.video/video6zvimpy52/idqnum65yr01"
			   }
			]
		 },
		{
		   "number": "",
		   "title": "Episodio 11",
		   "links": [
			   {
				"url": "https://wstream.video/video6zvimpy52/ny2cebs69d99"
			   }
			]
		 },
    	{
		   "number": "",
		   "title": "Episodio 12",
		   "links": [
			   {
				"url": "https://wstream.video/video6zvimpy52/38hbquxe7xg1"
			   }
			]
		 },
    	{
		   "number": "",
		   "title": "Episodio 13",
		   "links": [
			   {
				"url": "https://wstream.video/video6zvimpy52/liim6y9elc5v"
			   }
			]
		 },
    	{
		   "number": "",
		   "title": "Episodio 14",
		   "links": [
			   {
				"url": "https://wstream.video/video6zvimpy52/yf6fkl032xix"
			   }
			]
		 },
    	{
		   "number": "",
		   "title": "Episodio 15",
		   "links": [
			   {
				"url": "https://wstream.video/video6zvimpy52/o5z3j08dss5w"
			   }
			]
		 },
    	{
		   "number": "",
		   "title": "Episodio 16",
		   "links": [
			   {
				"url": "https://wstream.video/video6zvimpy52/32rvaj1o17dt"
			   }
			]
		 },
    	{
		   "number": "",
		   "title": "Episodio 17",
		   "links": [
			   {
				"url": "https://wstream.video/video6zvimpy52/6ihgbqoe9bh8"
			   }
			]
		 },
    	{
		   "number": "",
		   "title": "Episodio 18",
		   "links": [
			   {
				"url": "https://wstream.video/video6zvimpy52/aebowq2z3ruw"
			   }
			]
		 },
    	{
		   "number": "",
		   "title": "Episodio 19",
		   "links": [
			   {
				"url": "https://wstream.video/video6zvimpy52/8hrelpy4q8r6"
			   }
			]
		 },
    	{
		   "number": "",
		   "title": "Episodio 20",
		   "links": [
			   {
				"url": "https://wstream.video/video6zvimpy52/z3bto1440jyt"
			   }
			]
		 }
     ]
}  
